merk_api-0.0.6.dist-info/DESCRIPTION.rst
merk_api-0.0.6.dist-info/METADATA
merk_api-0.0.6.dist-info/RECORD
merk_api-0.0.6.dist-info/WHEEL
merk_api-0.0.6.dist-info/metadata.json
merk_api-0.0.6.dist-info/top_level.txt
merkapi/__init__.py
merkapi/utils.py
tests_merkapi/__init__.py
tests_merkapi/test_api.py
tests_merkapi/utils.py
