Metadata-Version: 2.0
Name: merk-api
Version: 0.0.6
Summary: Merk API Python client
Home-page: https://api.merk.cz/docs/
Author: Vitek Pliska
Author-email: vitek@creatiweb.cz
License: BSD
Platform: UNKNOWN
Classifier: Development Status :: 4 - Beta
Classifier: License :: OSI Approved :: BSD License
Classifier: Operating System :: OS Independent
Classifier: Programming Language :: Python
Classifier: Programming Language :: Python :: 2
Classifier: Programming Language :: Python :: 3
Classifier: Topic :: Utilities
Requires-Dist: certifi
Requires-Dist: msgpack-python
Requires-Dist: urllib3
